build/lib/build/lib/build/lib/build/lib/config/settings.py
build/lib/build/lib/build/lib/build/lib/config/urls.py
build/lib/build/lib/build/lib/build/lib/huscy/project_archivenotes/__init__.py
build/lib/build/lib/build/lib/build/lib/huscy/project_archivenotes/admin.py
build/lib/build/lib/build/lib/build/lib/huscy/project_archivenotes/apps.py
build/lib/build/lib/build/lib/build/lib/huscy/project_archivenotes/models.py
build/lib/build/lib/build/lib/build/lib/huscy/project_archivenotes/serializer.py
build/lib/build/lib/build/lib/build/lib/huscy/project_archivenotes/services.py
build/lib/build/lib/build/lib/build/lib/huscy/project_archivenotes/urls.py
build/lib/build/lib/build/lib/build/lib/huscy/project_archivenotes/views.py
build/lib/build/lib/build/lib/build/lib/huscy/project_archivenotes/migrations/0001_initial.py
build/lib/build/lib/build/lib/build/lib/huscy/project_archivenotes/migrations/__init__.py
build/lib/build/lib/build/lib/build/lib/tests/conftest.py
build/lib/build/lib/build/lib/build/lib/tests/viewsets/test_archivenote_viewset_create_archivenote.py
build/lib/build/lib/build/lib/build/lib/tests/viewsets/test_archivenote_viewset_delete_archivenote.py
build/lib/build/lib/build/lib/build/lib/tests/viewsets/test_archivenote_viewset_update_archivenote.py
build/lib/build/lib/build/lib/build/lib/tests/viewsets/test_archivenote_viewset_view_archivenote.py
build/lib/build/lib/build/lib/config/settings.py
build/lib/build/lib/build/lib/config/urls.py
build/lib/build/lib/build/lib/huscy/project_archivenotes/__init__.py
build/lib/build/lib/build/lib/huscy/project_archivenotes/admin.py
build/lib/build/lib/build/lib/huscy/project_archivenotes/apps.py
build/lib/build/lib/build/lib/huscy/project_archivenotes/models.py
build/lib/build/lib/build/lib/huscy/project_archivenotes/serializer.py
build/lib/build/lib/build/lib/huscy/project_archivenotes/services.py
build/lib/build/lib/build/lib/huscy/project_archivenotes/urls.py
huscy.project_archivenotes-0.1.0a4.dist-info/LICENSE
huscy.project_archivenotes-0.1.0a4.dist-info/METADATA
huscy.project_archivenotes-0.1.0a4.dist-info/WHEEL
huscy.project_archivenotes-0.1.0a4.dist-info/top_level.txt
huscy.project_archivenotes-0.1.0a4.dist-info/RECORD
